LICENSE
MANIFEST.in
README.md
setup.py
stanford_stk.egg-info/PKG-INFO
stanford_stk.egg-info/SOURCES.txt
stanford_stk.egg-info/dependency_links.txt
stanford_stk.egg-info/requires.txt
stanford_stk.egg-info/top_level.txt
stk/__init__.py
stk/matrix.py
stk/backend/__init__.py
stk/backend/autocast.py
stk/backend/sputnik.py
stk/backend/triton_kernels.py
stk/ops/__init__.py
stk/ops/eltwise_ops.py
stk/ops/eltwise_ops_test.py
stk/ops/linear_ops.py
stk/ops/linear_ops_test.py
stk/ops/matrix_ops.py
stk/ops/matrix_ops_test.py
stk/random/__init__.py
stk/random/random_ops.py
stk/random/random_ops_test.py