Metadata-Version: 2.1
Name: stanford-stk
Version: 0.0.7
Summary: Sparse Toolkit
Home-page: https://github.com/stanford-futuredata/stk
Author: Trevor Gale
Author-email: tgale@stanford.edu
License: UNKNOWN
Platform: UNKNOWN
Classifier: Programming Language :: Python :: 3
Classifier: License :: OSI Approved :: BSD License
Classifier: Operating System :: Unix
License-File: LICENSE
Requires-Dist: triton>=2.1.0
Provides-Extra: dev
Requires-Dist: absl-py; extra == "dev"
Provides-Extra: all
Requires-Dist: absl-py; extra == "all"
